{
    "total": {
        "date": "2026-04-08",
        "total_balance": 18466672.0,
        "cash_balance": 14697172.0,
        "stock_eval_amt": 3769500.0,
        "holdings_count": 4,
        "month_return": -2.62,
        "year_return": -2.62
    },
    "holdings": {
        "001120": {
            "name": "LX인터내셔널",
            "qty": 18,
            "buy_date": "2026-04-02",
            "holding_days": 6,
            "buy_price": 51266.6667,
            "current_price": 45950,
            "eval_amt": 827100,
            "return_rate": -10.37
        },
        "066970": {
            "name": "엘앤에프",
            "qty": 4,
            "buy_date": "2026-04-08",
            "holding_days": 0,
            "buy_price": 187900.0,
            "current_price": 182500,
            "eval_amt": 730000,
            "return_rate": -2.87
        },
        "082920": {
            "name": "비츠로셀",
            "qty": 24,
            "buy_date": "2026-04-02",
            "holding_days": 6,
            "buy_price": 39208.3333,
            "current_price": 38850,
            "eval_amt": 932400,
            "return_rate": -0.91
        },
        "095340": {
            "name": "ISC",
            "qty": 5,
            "buy_date": "2026-03-27",
            "holding_days": 12,
            "buy_price": 185320.0,
            "current_price": 256000,
            "eval_amt": 1280000,
            "return_rate": 38.14
        }
    },
    "exits_today": [
        {
            "stock_code": "112610",
            "name": "씨에스윈드",
            "buy_date": "2026-04-06",
            "sell_date": "2026-04-08",
            "qty": 12,
            "buy_price": 75333.3333,
            "return_rate": -13.45
        }
    ]
}