{
    "FINISH1": [
        {
            "code": "8928",
            "name": "Anabuki Kosan",
            "qty": 0,
            "balance": 0,
            "weight": 0.066,
            "status": "리밸런싱 매수실패"
        },
        {
            "code": "2693",
            "name": "YKT",
            "qty": 495.0000000000001,
            "balance": 201960.00000000003,
            "weight": 0.066,
            "status": "리밸런싱"
        },
        {
            "code": "7966",
            "name": "LINTEC",
            "qty": 0,
            "balance": 0,
            "weight": 0.066,
            "status": "리밸런싱 매수실패"
        },
        {
            "code": "8141",
            "name": "Shinko Shoji",
            "qty": 99.00000000000003,
            "balance": 156420.00000000003,
            "weight": 0.066,
            "status": "리밸런싱"
        },
        {
            "code": "5195",
            "name": "Bando Chemical Industries",
            "qty": 99.00000000000003,
            "balance": 216909.00000000006,
            "weight": 0.066,
            "status": "리밸런싱"
        },
        {
            "code": "4375",
            "name": "Safie",
            "qty": 297.00000000000006,
            "balance": 210870.00000000006,
            "weight": 0.066,
            "status": "리밸런싱"
        },
        {
            "code": "4286",
            "name": "Cl Holdings",
            "qty": 198.00000000000006,
            "balance": 212652.00000000006,
            "weight": 0.066,
            "status": "리밸런싱"
        },
        {
            "code": "8887",
            "name": "Syla Holdings",
            "qty": 693.0000000000001,
            "balance": 235620.00000000006,
            "weight": 0.066,
            "status": "리밸런싱"
        },
        {
            "code": "6149",
            "name": "Odawara Engineering",
            "qty": 99.00000000000003,
            "balance": 204237.00000000006,
            "weight": 0.066,
            "status": "리밸런싱"
        },
        {
            "code": "7887",
            "name": "Nankai Plywood",
            "qty": 99.00000000000003,
            "balance": 155628.00000000003,
            "weight": 0.066,
            "status": "리밸런싱"
        },
        {
            "code": "3723",
            "name": "Nihon Falcom",
            "qty": 99.00000000000003,
            "balance": 231858.00000000006,
            "weight": 0.066,
            "status": "리밸런싱"
        },
        {
            "code": "7463",
            "name": "Advan Group",
            "qty": 198.00000000000006,
            "balance": 178992.00000000003,
            "weight": 0.066,
            "status": "리밸런싱"
        }
    ],
    "hedge_gold": [
        {
            "code": "1328",
            "name": "Nomura NF Gold",
            "qty": 42.0,
            "balance": 716100.0,
            "weight": 0.2,
            "status": "리밸런싱"
        }
    ],
    "hedge_bond": [
        {
            "code": "1482",
            "name": "iShares JGB 7-10Y",
            "qty": 0,
            "balance": 0,
            "weight": 0.0,
            "status": "리밸런싱 매수실패"
        }
    ]
}